boardwatch_models/__init__.py
boardwatch_models/board.py
boardwatch_models/game.py
boardwatch_models/listing.py
boardwatch_models/platform.py
boardwatch_models/platform_edition.py
boardwatch_models/platform_name_group.py
boardwatch_models/user.py
boardwatch_models-0.14.0.dist-info/LICENSE
boardwatch_models-0.14.0.dist-info/METADATA
boardwatch_models-0.14.0.dist-info/WHEEL
boardwatch_models-0.14.0.dist-info/top_level.txt
boardwatch_models-0.14.0.dist-info/RECORD
